nr/io/graphviz/__init__.py
nr/io/graphviz/py.typed
nr/io/graphviz/render.py
nr/io/graphviz/writer.py
nr.io.graphviz-0.1.0.dist-info/LICENSE
nr.io.graphviz-0.1.0.dist-info/WHEEL
nr.io.graphviz-0.1.0.dist-info/METADATA
nr.io.graphviz-0.1.0.dist-info/RECORD
